{
  "main": {
    "id": "38833e9874ee40e7",
    "type": "split",
    "children": [
      {
        "id": "db72512d6edf1fb2",
        "type": "tabs",
        "children": [
          {
            "id": "ca7cc9cfc71a8e4d",
            "type": "leaf",
            "pinned": true,
            "state": {
              "type": "markdown",
              "state": {
                "file": "Areas/Projects/A star/A Star algorithm vid notes.md",
                "mode": "preview",
                "backlinks": false,
                "source": false
              },
              "pinned": true
            }
          },
          {
            "id": "389783fe6707a650",
            "type": "leaf",
            "pinned": true,
            "state": {
              "type": "markdown",
              "state": {
                "file": "Areas/Projects/A star/PseudoCode for A*.md",
                "mode": "source",
                "backlinks": false,
                "source": false
              },
              "pinned": true
            }
          },
          {
            "id": "8f14825a79ffb48c",
            "type": "leaf",
            "state": {
              "type": "markdown",
              "state": {
                "file": "Areas/Projects/A star/implementation.md",
                "mode": "source",
                "backlinks": false,
                "source": false
              }
            }
          }
        ],
        "currentTab": 2
      }
    ],
    "direction": "vertical"
  },
  "left": {
    "id": "3348ca123ad4ba47",
    "type": "split",
    "children": [
      {
        "id": "e0aa37c5eb419e43",
        "type": "tabs",
        "children": [
          {
            "id": "0d9a2f8aed13fdbc",
            "type": "leaf",
            "state": {
              "type": "search",
              "state": {
                "query": "tag:#resource",
                "matchingCase": false,
                "explainSearch": false,
                "collapseAll": false,
                "extraContext": false,
                "sortOrder": "alphabetical"
              }
            }
          },
          {
            "id": "f9ab71fc25a436d2",
            "type": "leaf",
            "state": {
              "type": "git-view",
              "state": {}
            }
          },
          {
            "id": "67ef5afbee5fb6c8",
            "type": "leaf",
            "state": {
              "type": "file-explorer",
              "state": {
                "sortOrder": "alphabetical"
              }
            }
          },
          {
            "id": "7a3707bc446fb6fd",
            "type": "leaf",
            "state": {
              "type": "bookmarks",
              "state": {}
            }
          }
        ],
        "currentTab": 1
      }
    ],
    "direction": "horizontal",
    "width": 300
  },
  "right": {
    "id": "ea3504fd1de54a14",
    "type": "split",
    "children": [
      {
        "id": "bf19661f729d6ff7",
        "type": "tabs",
        "children": [
          {
            "id": "703eba2feea725e3",
            "type": "leaf",
            "state": {
              "type": "backlink",
              "state": {
                "file": "Areas/Projects/A star/implementation.md",
                "collapseAll": false,
                "extraContext": false,
                "sortOrder": "alphabetical",
                "showSearch": false,
                "searchQuery": "",
                "backlinkCollapsed": true,
                "unlinkedCollapsed": true
              }
            }
          },
          {
            "id": "dab8911558a29618",
            "type": "leaf",
            "state": {
              "type": "outgoing-link",
              "state": {
                "file": "Areas/Projects/A star/implementation.md",
                "linksCollapsed": false,
                "unlinkedCollapsed": true
              }
            }
          },
          {
            "id": "e52e0e0a9e5d8016",
            "type": "leaf",
            "state": {
              "type": "tag",
              "state": {
                "sortOrder": "frequency",
                "useHierarchy": true
              }
            }
          },
          {
            "id": "6b1190ecdba4494d",
            "type": "leaf",
            "state": {
              "type": "outline",
              "state": {
                "file": "Areas/Projects/A star/implementation.md"
              }
            }
          }
        ],
        "currentTab": 3
      }
    ],
    "direction": "horizontal",
    "width": 300,
    "collapsed": true
  },
  "left-ribbon": {
    "hiddenItems": {
      "obsidian-excalidraw-plugin:Create new drawing": false,
      "markdown-importer:Open format converter": false,
      "switcher:Open quick switcher": false,
      "canvas:Create new canvas": false,
      "daily-notes:Open today's daily note": false,
      "templates:Insert template": false,
      "graph:Open graph view": false,
      "command-palette:Open command palette": false
    }
  },
  "active": "f9ab71fc25a436d2",
  "lastOpenFiles": [
    "Areas/Projects/A star/A Star algorithm vid notes.md",
    "Areas/Projects/A star/PseudoCode for A*.md",
    "Resources/assorted media/Excalidraw/code into linked list.md",
    "Areas/Projects/A star/implementation.md",
    "Areas/Projects/LeetCode/Data structures/Linked list.md",
    "Areas/Projects/LeetCode/algorithms/Floyd's tortoise and hare.md",
    "Areas/Projects/LeetCode/algorithms/Binary search.md",
    "Areas/Projects/LeetCode/Questions/12. Integer to Roman.md",
    "Areas/Projects/LeetCode/Questions/20. Valid Parentheses-Stack data structures.md",
    "Areas/Projects/LeetCode/Questions/141. Linked List Cycle.md",
    "Areas/Projects/LeetCode/Questions/167. Two Sum II - Input Array Is Sorted.md",
    "Areas/Projects/LeetCode/Questions/217. Contains Duplicate.md",
    "Areas/Projects/LeetCode/Questions/Two Sum.md",
    "Areas/Projects/LeetCode/Questions/TwoPointers-PalindroneNumbers.md",
    "Archives/Projects/Robot arm.md",
    "Areas/Projects/Hasso Plattner/Professer interview.md",
    "Areas/Projects/Hasso Plattner/Reaserch info.md",
    "Areas/Projects/Space Traders/Brain dump.md",
    "Areas/Projects/Space Traders/Front End.md",
    "Areas/Projects/Space Traders/Rest Api.md",
    "Archives/Projects/PID/Wiring And planning.md",
    "Archives/Projects/PID/PID resource links.md",
    "Archives/Projects/PID/PID Code Documentation.md",
    "Areas/Projects/Hasso Plattner",
    "Areas/Projects/Space Traders/Untitled.md",
    "Resources/Note taking/markdown-cheat-sheet.md",
    "Resources/Python Docs/Functions and Operators.md",
    "Resources/Note taking",
    "Resources/Library Documentation",
    "Archives/Projects",
    "Areas/Projects/Space Traders",
    "Untitled",
    "Areas/Projects/LeetCode/Data structures",
    "desktop.ini",
    "Resources/assorted media/Pasted Image 20230613195002_207.png",
    "Resources/assorted media/Excalidraw",
    "Areas/Projects/LeetCode/algorithms",
    "Untitled.canvas",
    "Resources/assorted media/Layer~1.Multiply.100.Visible.png",
    "Resources/assorted media/GRAPH EXAMPLE.png",
    "Resources/assorted media/Pasted image 20221009214700.png",
    "Resources/assorted media/copy-list-in-python.png"
  ]
}